README
setup.py
classfield/__init__.py
classfield/fields.py
django_classfield.egg-info/PKG-INFO
django_classfield.egg-info/SOURCES.txt
django_classfield.egg-info/dependency_links.txt
django_classfield.egg-info/pbr.json
django_classfield.egg-info/top_level.txt