Metadata-Version: 1.1
Name: django-classfield
Version: 1.1.7
Summary: Adds a class field to django
Home-page: https://github.com/MikeAmy/django-classfield
Author: Mike Harris, Mike Amy
Author-email: michael.amy@wfp.org
License: MIT
Platform: UNKNOWN
Classifier: License :: OSI Approved :: MIT License
